sqlshield/__init__.py
sqlshield/models.cpython-38-x86_64-linux-gnu.so
sqlshield/shield.cpython-38-x86_64-linux-gnu.so
sqlshield-0.0.23.dist-info/LICENSE
sqlshield-0.0.23.dist-info/METADATA
sqlshield-0.0.23.dist-info/WHEEL
sqlshield-0.0.23.dist-info/top_level.txt
sqlshield-0.0.23.dist-info/RECORD
