Metadata-Version: 2.1
Name: sqlshield
Version: 0.0.23
Summary: A Shield for your LLM generated SQL Queries. It provides an application level control for securing the database from SQL generated by LLM.
Author: Sandeep Giri
Author-email: sandeepgiri@gmail.com
Project-URL: Documentation, https://github.com/terno-ai/llm-sql-shield/README.md
Project-URL: Source, https://github.com/terno-ai/llm-sql-shield
Project-URL: Tracker, https://github.com/terno-ai/llm-sql-shield/issues
Classifier: Programming Language :: Python :: 3
Classifier: Programming Language :: Python :: 3.8
Classifier: Programming Language :: Python :: 3.9
Classifier: Programming Language :: Python :: 3.10
Classifier: Programming Language :: Python :: 3.11
Classifier: Programming Language :: Python :: 3.12
Classifier: Operating System :: OS Independent
Classifier: License :: OSI Approved :: Apache Software License
Requires-Python: >=3.8
License-File: LICENSE
